rixs/__init__.py
rixs/_version.py
rixs/plotting_functions.py
rixs/process2d.py
rixs/tests/__init__.py
rixs/tests/conftest.py
rixs/tests/test_process2d.py
rixs-0.0.3.dist-info/AUTHORS.rst
rixs-0.0.3.dist-info/LICENSE
rixs-0.0.3.dist-info/METADATA
rixs-0.0.3.dist-info/WHEEL
rixs-0.0.3.dist-info/entry_points.txt
rixs-0.0.3.dist-info/top_level.txt
rixs-0.0.3.dist-info/RECORD
