Metadata-Version: 2.1
Name: rixs
Version: 0.0.3
Summary: Analysis tools for resonant inelastic xray scattering.
Home-page: https://github.com/awalter-bnl/rixs
Author: Brookhaven National Lab
Author-email: awalter@bnl.gov
License: BSD (3-clause)
Platform: UNKNOWN
Classifier: Development Status :: 2 - Pre-Alpha
Classifier: Natural Language :: English
Classifier: Programming Language :: Python :: 3
Requires-Dist: matplotlib
Requires-Dist: numpy
Requires-Dist: pandas
Requires-Dist: scipy
